[
  {
    "mop_up":"no",
    "household_type":"ordinary_household",
    "sprayed":"yes",
    "number_sprayable_rooms":4,
    "number_sprayed":2,
    "number_unsprayed":2,
    "chemical_used":"ddt",
    "total_population":3,
    "under_five":2,
    "over_five":1,
    "hh_name":"name"
  },
  {
    "mop_up":"no",
    "household_type":"ordinary_household",
    "sprayed":"partial",
    "number_sprayable_rooms":3,
    "number_sprayed":3,
    "number_unsprayed":0,
    "chemical_used":"ddt",
    "total_population":2,
    "under_five":1,
    "over_five":1,
    "hh_name":"name",
    "reason_unsprayed":"locked"
  },
  {
    "household_type":"ordinary_household",
    "mop_up":"no",
    "sprayed":"no",
    "number_sprayable_rooms":2,
    "reason_unsprayed":"refused",
    "hh_name":"name"
  }
]
